DpyToolHandle/__init__.py
DpyToolHandle/setup.py
dpytoolhandle-0.0.1.dist-info/METADATA
dpytoolhandle-0.0.1.dist-info/WHEEL
dpytoolhandle-0.0.1.dist-info/top_level.txt
dpytoolhandle-0.0.1.dist-info/RECORD
